womb/___objectives/OSM/OSM.S.HTML
womb/___objectives/objectives.S.HTML
womb/__dictionary/womb_1
womb/__init__.py
womb/__licenses/license.S.HTML
womb/__licenses/licenses/gpl-3.0-standalone.html
womb/__licenses/licenses/non-business.S.HTML
womb/_essence/__init__.py
womb/_essence/essence.S.HTML
womb/_essence/merge/__init__.py
womb/_essence/scan/__init__.py
womb/_essence/seek/__init__.py
womb/_internal_status/DB/records.json
womb/_internal_status/internal_status.S.HTML
womb/_internal_status/monitors/status_1.py
womb/_internal_status/status.proc.py
womb/_ops/_clique/__init__.py
womb/_ops/_clique/group/__init__.py
womb/adventures/_ops/clique.py
womb/adventures/_ops/off.py
womb/adventures/_ops/on.py
womb/adventures/_ops/refresh.py
womb/adventures/_ops/status.py
womb/adventures/alerting/__init__.py
womb/adventures/alerting/parse_exception.py
womb/adventures/monetary/.gitignore
womb/adventures/monetary/__init__.py
womb/adventures/monetary/__saves/saves.S.HTML
womb/adventures/monetary/_ops/_clique.py
womb/adventures/monetary/_ops/off.py
womb/adventures/monetary/_ops/on.py
womb/adventures/monetary/_ops/saves/_clique.py
womb/adventures/monetary/_ops/saves/dumps/dump.py
womb/adventures/monetary/_ops/saves/dumps/restore.py
womb/adventures/monetary/_ops/saves/exports/export.py
womb/adventures/monetary/_ops/saves/exports/import.py
womb/adventures/monetary/_ops/saves/memories.S.HTML
womb/adventures/monetary/_ops/status.py
womb/adventures/monetary/databases/mesmerizing/connect.py
womb/adventures/monetary/databases/mesmerizing/places/insert.py
womb/adventures/monetary/monetary.S.HTML
womb/adventures/monetary/moves/URL/retrieve.py
womb/adventures/sanique/_ops/off.py
womb/adventures/sanique/_ops/on.py
womb/adventures/sanique/_ops/refresh.py
womb/adventures/sanique/_ops/status.py
womb/adventures/sanique/_status/API_status_besties__food_USDA__nature_v2__FDC_ID_1.py
womb/adventures/sanique/clique.py
womb/adventures/sanique/harbor/__init__.py
womb/adventures/sanique/play/__init__.py
womb-1.0.2.dist-info/METADATA
womb-1.0.2.dist-info/WHEEL
womb-1.0.2.dist-info/entry_points.txt
womb-1.0.2.dist-info/RECORD
